README.txt
setup.py
Products/__init__.py
Products.AccessibleReferenceBrowserWidget.egg-info/PKG-INFO
Products.AccessibleReferenceBrowserWidget.egg-info/SOURCES.txt
Products.AccessibleReferenceBrowserWidget.egg-info/dependency_links.txt
Products.AccessibleReferenceBrowserWidget.egg-info/entry_points.txt
Products.AccessibleReferenceBrowserWidget.egg-info/namespace_packages.txt
Products.AccessibleReferenceBrowserWidget.egg-info/not-zip-safe
Products.AccessibleReferenceBrowserWidget.egg-info/requires.txt
Products.AccessibleReferenceBrowserWidget.egg-info/top_level.txt
Products/AccessibleReferenceBrowserWidget/__init__.py
Products/AccessibleReferenceBrowserWidget/allow.py
Products/AccessibleReferenceBrowserWidget/changes.txt
Products/AccessibleReferenceBrowserWidget/configure.zcml
Products/AccessibleReferenceBrowserWidget/implements_arbw.py
Products/AccessibleReferenceBrowserWidget/interfaces.py
Products/AccessibleReferenceBrowserWidget/readme.txt
Products/AccessibleReferenceBrowserWidget/translations.py
Products/AccessibleReferenceBrowserWidget/zope2.py
Products/AccessibleReferenceBrowserWidget/i18n/accessiblereferencebrowserwidget-no.mo
Products/AccessibleReferenceBrowserWidget/i18n/accessiblereferencebrowserwidget-no.po
Products/AccessibleReferenceBrowserWidget/profiles/default/actions.xml
Products/AccessibleReferenceBrowserWidget/profiles/default/metadata.xml
Products/AccessibleReferenceBrowserWidget/profiles/default/portlets.xml
Products/AccessibleReferenceBrowserWidget/profiles/default/skins.xml
Products/AccessibleReferenceBrowserWidget/skins/AccessibleReferenceBrowserWidget/get_reference_field.py
Products/AccessibleReferenceBrowserWidget/skins/AccessibleReferenceBrowserWidget/reference_browser.pt
Products/AccessibleReferenceBrowserWidget/skins/AccessibleReferenceBrowserWidget/reference_browser_available.py
Products/AccessibleReferenceBrowserWidget/skins/AccessibleReferenceBrowserWidget/reference_field_set.py
dist/Products.AccessibleReferenceBrowserWidget-1.0a.tar.gz
docs/HISTORY.txt
docs/INSTALL.txt
docs/LICENSE.GPL
docs/LICENSE.txt