Metadata-Version: 1.0
Name: Products.AccessibleReferenceBrowserWidget
Version: 1.0a
Summary: Provides an accessible (for visually impaired) users based on HTML only (no Javascript).
Home-page: http://www.nidelven-it.no/d
Author: Morten W. Petersen
Author-email: morten@nidelven-it.no
License: GPL
Keywords: python zope plone accessibility reference
Platform: UNKNOWN
Classifier: Framework :: Plone
Classifier: Programming Language :: Python
